napari_sairyscan/__init__.py
napari_sairyscan/_dict_widget.py
napari_sairyscan/_enhancing_widget.py
napari_sairyscan/_ifed.py
napari_sairyscan/_isfed.py
napari_sairyscan/_ism.py
napari_sairyscan/_pipelines.py
napari_sairyscan/_pseudo_confocal.py
napari_sairyscan/_psf_widget.py
napari_sairyscan/_reader.py
napari_sairyscan/_registration_widget.py
napari_sairyscan/_sample_data.py
napari_sairyscan/_spitfire_join_deconv.py
napari_sairyscan/_splugin.py
napari_sairyscan/_widget.py
napari_sairyscan/napari.yaml
napari_sairyscan/_tests/__init__.py
napari_sairyscan/_tests/test_reader.py
napari_sairyscan/_tests/test_sample_data.py
napari_sairyscan/_tests/test_widget.py
napari_sairyscan/_tests/test_writer.py
napari_sairyscan-0.0.2.dist-info/LICENSE
napari_sairyscan-0.0.2.dist-info/METADATA
napari_sairyscan-0.0.2.dist-info/WHEEL
napari_sairyscan-0.0.2.dist-info/entry_points.txt
napari_sairyscan-0.0.2.dist-info/top_level.txt
napari_sairyscan-0.0.2.dist-info/RECORD
