Metadata-Version: 2.1
Name: napari-sairyscan
Version: 0.0.2
Summary: Airyscan image reconstruction
Home-page: https://github.com/sylvainprigent/napari-sairyscan
Author: Sylvain Prigent
Author-email: meriadec.prigent@gmail.com
License: BSD-3-Clause
Project-URL: Bug Tracker, https://github.com/sylvainprigent/napari-sairyscan/issues
Project-URL: Documentation, https://github.com/sylvainprigent/napari-sairyscan#README.md
Project-URL: Source Code, https://github.com/sylvainprigent/napari-sairyscan
Project-URL: User Support, https://github.com/sylvainprigent/napari-sairyscan/issues
Classifier: Development Status :: 2 - Pre-Alpha
Classifier: Intended Audience :: Developers
Classifier: Framework :: napari
Classifier: Topic :: Software Development :: Testing
Classifier: Programming Language :: Python
Classifier: Programming Language :: Python :: 3
Classifier: Programming Language :: Python :: 3.8
Classifier: Programming Language :: Python :: 3.9
Classifier: Programming Language :: Python :: 3.10
Classifier: Operating System :: OS Independent
Classifier: License :: OSI Approved :: BSD License
Requires-Python: >=3.8
License-File: LICENSE
Requires-Dist: numpy
Requires-Dist: magicgui
Requires-Dist: qtpy
Requires-Dist: sairyscan (>=0.0.2)
Provides-Extra: testing
Requires-Dist: tox ; extra == 'testing'
Requires-Dist: pytest ; extra == 'testing'
Requires-Dist: pytest-cov ; extra == 'testing'
Requires-Dist: pytest-qt ; extra == 'testing'
Requires-Dist: napari ; extra == 'testing'
Requires-Dist: pyqt5 ; extra == 'testing'
